{
  "interests": [
    {
      "label": "Javascript",
      "image": {
        "src": "../../images/js.png",
        "alt": ""
      }
    },
    {
      "label": "React",
      "image": {
        "src": "../../images/react.png",
        "alt": ""
      }
    },
    {
      "label": "Travel",
      "image": {
        "src": "../../images/mountain.png",
        "alt": ""
      }
    },
    {
      "label": "Gaming",
      "image": {
        "src": "../../images/joystick.png",
        "alt": ""
      }
    }
  ],
  "button": {
    "visible": false,
    "label": "+ Load More",
    "initiallyShownInterests": 5
  }
}
